<xml xmlns="http://www.w3.org/1999/xhtml">
  <block type="movement_forward" id="1" x="-54" y="12">
    <next>
      <block type="controls_whileUntil" id="2" inline="false">
        <field name="MODE">WHILE</field>
        <value name="NUMBER">
          <block type="math_number" id="3">
            <field name="NUM">1</field>
          </block>
        </value>
        <statement name="DO">
          <block type="robot_delay" id="4" inline="true">
            <value name="DELAY">
              <block type="math_number" id="5">
                <field name="NUM">1800</field>
              </block>
            </value>
            <next>
              <block type="movement_right" id="6">
                <next>
                  <block type="controls_whileUntil" id="7" inline="false">
                    <field name="MODE">WHILE</field>
                    <value name="NUMBER">
                      <block type="math_number" id="8">
                        <field name="NUM">1</field>
                      </block>
                    </value>
                    <statement name="DO">
                      <block type="robot_delay" id="9" inline="true">
                        <value name="DELAY">
                          <block type="math_number" id="10">
                            <field name="NUM">1450</field>
                          </block>
                        </value>
                        <next>
                          <block type="movement_forward" id="11">
                            <next>
                              <block type="controls_whileUntil" id="12" inline="false">
                                <field name="MODE">WHILE</field>
                                <value name="NUMBER">
                                  <block type="math_number" id="13">
                                    <field name="NUM">1</field>
                                  </block>
                                </value>
                                <statement name="DO">
                                  <block type="robot_delay" id="14" inline="true">
                                    <value name="DELAY">
                                      <block type="math_number" id="15">
                                        <field name="NUM">1800</field>
                                      </block>
                                    </value>
                                    <next>
                                      <block type="movement_right" id="16">
                                        <next>
                                          <block type="controls_whileUntil" id="17" inline="false">
                                            <field name="MODE">WHILE</field>
                                            <value name="NUMBER">
                                              <block type="math_number" id="18">
                                                <field name="NUM">1</field>
                                              </block>
                                            </value>
                                            <statement name="DO">
                                              <block type="robot_delay" id="19" inline="true">
                                                <value name="DELAY">
                                                  <block type="math_number" id="20">
                                                    <field name="NUM">1450</field>
                                                  </block>
                                                </value>
                                                <next>
                                                  <block type="movement_forward" id="21">
                                                    <next>
                                                      <block type="controls_whileUntil" id="22" inline="false">
                                                        <field name="MODE">WHILE</field>
                                                        <value name="NUMBER">
                                                          <block type="math_number" id="23">
                                                            <field name="NUM">1</field>
                                                          </block>
                                                        </value>
                                                        <statement name="DO">
                                                          <block type="robot_delay" id="24" inline="true">
                                                            <value name="DELAY">
                                                              <block type="math_number" id="25">
                                                                <field name="NUM">1800</field>
                                                              </block>
                                                            </value>
                                                            <next>
                                                              <block type="movement_left" id="51">
                                                                <next>
                                                                  <block type="controls_whileUntil" id="27" inline="false">
                                                                    <field name="MODE">WHILE</field>
                                                                    <value name="NUMBER">
                                                                      <block type="math_number" id="28">
                                                                        <field name="NUM">1</field>
                                                                      </block>
                                                                    </value>
                                                                    <statement name="DO">
                                                                      <block type="robot_delay" id="29" inline="true">
                                                                        <value name="DELAY">
                                                                          <block type="math_number" id="30">
                                                                            <field name="NUM">1450</field>
                                                                          </block>
                                                                        </value>
                                                                        <next>
                                                                          <block type="movement_forward" id="31">
                                                                            <next>
                                                                              <block type="controls_whileUntil" id="32" inline="false">
                                                                                <field name="MODE">WHILE</field>
                                                                                <value name="NUMBER">
                                                                                  <block type="math_number" id="33">
                                                                                    <field name="NUM">1</field>
                                                                                  </block>
                                                                                </value>
                                                                                <statement name="DO">
                                                                                  <block type="robot_delay" id="34" inline="true">
                                                                                    <value name="DELAY">
                                                                                      <block type="math_number" id="35">
                                                                                        <field name="NUM">1800</field>
                                                                                      </block>
                                                                                    </value>
                                                                                    <next>
                                                                                      <block type="movement_stutter" id="61"></block>
                                                                                    </next>
                                                                                  </block>
                                                                                </statement>
                                                                              </block>
                                                                            </next>
                                                                          </block>
                                                                        </next>
                                                                      </block>
                                                                    </statement>
                                                                  </block>
                                                                </next>
                                                              </block>
                                                            </next>
                                                          </block>
                                                        </statement>
                                                      </block>
                                                    </next>
                                                  </block>
                                                </next>
                                              </block>
                                            </statement>
                                          </block>
                                        </next>
                                      </block>
                                    </next>
                                  </block>
                                </statement>
                              </block>
                            </next>
                          </block>
                        </next>
                      </block>
                    </statement>
                  </block>
                </next>
              </block>
            </next>
          </block>
        </statement>
      </block>
    </next>
  </block>
</xml>